<?xml version="1.0" encoding="UTF-8"?>
<!DOCTYPE mapper PUBLIC "-//mybatis.org//DTD Mapper 3.0//EN" "http://mybatis.org/dtd/mybatis-3-mapper.dtd">
<mapper namespace="com.trkj.crmproject.dao.wentao.IndentShipmentsDetailDao">
  <resultMap id="BaseResultMap" type="com.trkj.crmproject.entity.wentao.IndentShipmentsDetail">
    <id column="id" jdbcType="VARCHAR" property="id" />
    <result column="indent_shipments_id" jdbcType="VARCHAR" property="indentShipmentsId" />
    <result column="product_id" jdbcType="VARCHAR" property="productId" />
    <result column="product_name" jdbcType="VARCHAR" property="productName" />
    <result column="unit_price" jdbcType="DECIMAL" property="unitPrice" />
    <result column="money" jdbcType="DECIMAL" property="money" />
    <result column="quantity" jdbcType="INTEGER" property="quantity" />
    <result column="remark" jdbcType="VARCHAR" property="remark" />
    <result column="model" jdbcType="VARCHAR" property="model" />
    <result column="AddName" jdbcType="VARCHAR" property="addname" />
    <result column="AddTime" jdbcType="TIMESTAMP" property="addtime" />
    <result column="UpdateName" jdbcType="VARCHAR" property="updatename" />
    <result column="UpdateTime" jdbcType="TIMESTAMP" property="updatetime" />
    <result column="DeleteName" jdbcType="VARCHAR" property="deletename" />
    <result column="DeleteTime" jdbcType="TIMESTAMP" property="deletetime" />
    <result column="TimeLiness" jdbcType="INTEGER" property="timeliness" />
  </resultMap>
  <sql id="Base_Column_List">
    id, indent_shipments_id, product_id, product_name, unit_price, money, quantity, remark, 
    model, AddName, AddTime, UpdateName, UpdateTime, DeleteName, DeleteTime, TimeLiness
  </sql>
  <select id="selectByPrimaryKey" parameterType="java.lang.String" resultMap="BaseResultMap">
    select 
    <include refid="Base_Column_List" />
    from indent_shipments_detail
    where id = #{id,jdbcType=VARCHAR}
  </select>
  <delete id="deleteByPrimaryKey" parameterType="java.lang.String">
    delete from indent_shipments_detail
    where id = #{id,jdbcType=VARCHAR}
  </delete>
  <insert id="insert" parameterType="java.util.List">
    insert into indent_shipments_detail (id,indent_shipments_id, product_id, product_name,
      unit_price, money, quantity, 
      remark, model, AddName, 
      AddTime, UpdateName, UpdateTime, 
      DeleteName, DeleteTime, TimeLiness
      )
    values
    <foreach collection="list" item="item" separator=",">
    (#{item.id,jdbcType=VARCHAR},#{item.indentShipmentsId,jdbcType=VARCHAR}, #{item.productId,jdbcType=VARCHAR}, #{item.productName,jdbcType=VARCHAR},
      #{item.unitPrice,jdbcType=DECIMAL}, #{item.money,jdbcType=DECIMAL}, #{item.quantity,jdbcType=INTEGER},
      #{item.remark,jdbcType=VARCHAR}, #{item.model,jdbcType=VARCHAR}, #{item.addname,jdbcType=VARCHAR},
      #{item.addtime,jdbcType=TIMESTAMP}, #{item.updatename,jdbcType=VARCHAR}, #{item.updatetime,jdbcType=TIMESTAMP},
      #{item.deletename,jdbcType=VARCHAR}, #{item.deletetime,jdbcType=TIMESTAMP}, #{item.timeliness,jdbcType=INTEGER}
      )
    </foreach>
  </insert>
  <insert id="insertSelective" keyColumn="id" keyProperty="id" parameterType="com.trkj.crmproject.entity.wentao.IndentShipmentsDetail" useGeneratedKeys="true">
    insert into indent_shipments_detail
    <trim prefix="(" suffix=")" suffixOverrides=",">
      <if test="indentShipmentsId != null">
        indent_shipments_id,
      </if>
      <if test="productId != null">
        product_id,
      </if>
      <if test="productName != null">
        product_name,
      </if>
      <if test="unitPrice != null">
        unit_price,
      </if>
      <if test="money != null">
        money,
      </if>
      <if test="quantity != null">
        quantity,
      </if>
      <if test="remark != null">
        remark,
      </if>
      <if test="model != null">
        model,
      </if>
      <if test="addname != null">
        AddName,
      </if>
      <if test="addtime != null">
        AddTime,
      </if>
      <if test="updatename != null">
        UpdateName,
      </if>
      <if test="updatetime != null">
        UpdateTime,
      </if>
      <if test="deletename != null">
        DeleteName,
      </if>
      <if test="deletetime != null">
        DeleteTime,
      </if>
      <if test="timeliness != null">
        TimeLiness,
      </if>
    </trim>
    <trim prefix="values (" suffix=")" suffixOverrides=",">
      <if test="indentShipmentsId != null">
        #{indentShipmentsId,jdbcType=VARCHAR},
      </if>
      <if test="productId != null">
        #{productId,jdbcType=VARCHAR},
      </if>
      <if test="productName != null">
        #{productName,jdbcType=VARCHAR},
      </if>
      <if test="unitPrice != null">
        #{unitPrice,jdbcType=DECIMAL},
      </if>
      <if test="money != null">
        #{money,jdbcType=DECIMAL},
      </if>
      <if test="quantity != null">
        #{quantity,jdbcType=INTEGER},
      </if>
      <if test="remark != null">
        #{remark,jdbcType=VARCHAR},
      </if>
      <if test="model != null">
        #{model,jdbcType=VARCHAR},
      </if>
      <if test="addname != null">
        #{addname,jdbcType=VARCHAR},
      </if>
      <if test="addtime != null">
        #{addtime,jdbcType=TIMESTAMP},
      </if>
      <if test="updatename != null">
        #{updatename,jdbcType=VARCHAR},
      </if>
      <if test="updatetime != null">
        #{updatetime,jdbcType=TIMESTAMP},
      </if>
      <if test="deletename != null">
        #{deletename,jdbcType=VARCHAR},
      </if>
      <if test="deletetime != null">
        #{deletetime,jdbcType=TIMESTAMP},
      </if>
      <if test="timeliness != null">
        #{timeliness,jdbcType=INTEGER},
      </if>
    </trim>
  </insert>
  <update id="updateByPrimaryKeySelective" parameterType="com.trkj.crmproject.entity.wentao.IndentShipmentsDetail">
    update indent_shipments_detail
    <set>
      <if test="indentShipmentsId != null">
        indent_shipments_id = #{indentShipmentsId,jdbcType=VARCHAR},
      </if>
      <if test="productId != null">
        product_id = #{productId,jdbcType=VARCHAR},
      </if>
      <if test="productName != null">
        product_name = #{productName,jdbcType=VARCHAR},
      </if>
      <if test="unitPrice != null">
        unit_price = #{unitPrice,jdbcType=DECIMAL},
      </if>
      <if test="money != null">
        money = #{money,jdbcType=DECIMAL},
      </if>
      <if test="quantity != null">
        quantity = #{quantity,jdbcType=INTEGER},
      </if>
      <if test="remark != null">
        remark = #{remark,jdbcType=VARCHAR},
      </if>
      <if test="model != null">
        model = #{model,jdbcType=VARCHAR},
      </if>
      <if test="addname != null">
        AddName = #{addname,jdbcType=VARCHAR},
      </if>
      <if test="addtime != null">
        AddTime = #{addtime,jdbcType=TIMESTAMP},
      </if>
      <if test="updatename != null">
        UpdateName = #{updatename,jdbcType=VARCHAR},
      </if>
      <if test="updatetime != null">
        UpdateTime = #{updatetime,jdbcType=TIMESTAMP},
      </if>
      <if test="deletename != null">
        DeleteName = #{deletename,jdbcType=VARCHAR},
      </if>
      <if test="deletetime != null">
        DeleteTime = #{deletetime,jdbcType=TIMESTAMP},
      </if>
      <if test="timeliness != null">
        TimeLiness = #{timeliness,jdbcType=INTEGER},
      </if>
    </set>
    where id = #{id,jdbcType=VARCHAR}
  </update>
  <update id="updateByPrimaryKey" parameterType="com.trkj.crmproject.entity.wentao.IndentShipmentsDetail">
    update indent_shipments_detail
    set indent_shipments_id = #{indentShipmentsId,jdbcType=VARCHAR},
      product_id = #{productId,jdbcType=VARCHAR},
      product_name = #{productName,jdbcType=VARCHAR},
      unit_price = #{unitPrice,jdbcType=DECIMAL},
      money = #{money,jdbcType=DECIMAL},
      quantity = #{quantity,jdbcType=INTEGER},
      remark = #{remark,jdbcType=VARCHAR},
      model = #{model,jdbcType=VARCHAR},
      AddName = #{addname,jdbcType=VARCHAR},
      AddTime = #{addtime,jdbcType=TIMESTAMP},
      UpdateName = #{updatename,jdbcType=VARCHAR},
      UpdateTime = #{updatetime,jdbcType=TIMESTAMP},
      DeleteName = #{deletename,jdbcType=VARCHAR},
      DeleteTime = #{deletetime,jdbcType=TIMESTAMP},
      TimeLiness = #{timeliness,jdbcType=INTEGER}
    where id = #{id,jdbcType=VARCHAR}
  </update>
</mapper>